src/__init__.py
src/config.py
src/gui.py
src/main.py
src/utils.py
src/genshin/__init__.py
src/genshin/linux.py
genshin_account_switcher-1.2.2.dist-info/LICENSE
genshin_account_switcher-1.2.2.dist-info/METADATA
genshin_account_switcher-1.2.2.dist-info/WHEEL
genshin_account_switcher-1.2.2.dist-info/entry_points.txt
genshin_account_switcher-1.2.2.dist-info/top_level.txt
genshin_account_switcher-1.2.2.dist-info/RECORD
