Metadata-Version: 2.1
Name: genshin-account-switcher
Version: 1.2.2
Summary: Simple account switcher for Genshin Impact on Linux.
Home-page: https://github.com/atomicptr/genshin-account-switcher
Author: Christopher Kaster
Author-email: me@atomicptr.de
Classifier: Topic :: Games/Entertainment
Classifier: Operating System :: POSIX :: Linux
Classifier: License :: OSI Approved :: GNU General Public License v3 (GPLv3)
Requires-Python: >=3.10
License-File: LICENSE
Requires-Dist: appdirs (==1.4.4)
